snoweve/__init__.py
snoweve/snoweve.py
snoweve-0.0.1a0.dist-info/LICENSE
snoweve-0.0.1a0.dist-info/METADATA
snoweve-0.0.1a0.dist-info/WHEEL
snoweve-0.0.1a0.dist-info/top_level.txt
snoweve-0.0.1a0.dist-info/RECORD
