Metadata-Version: 2.1
Name: snoweve
Version: 0.0.1a0
Summary: Logical Regex
Home-page: https://gitlab.com/suganda8/snoweve
Author: Tegar Bangun Suganda
Author-email: tegarbangunsuganda@gmail.com
License: UNKNOWN
Platform: UNKNOWN
Classifier: Programming Language :: Python :: 3
Classifier: License :: OSI Approved :: GNU General Public License v3 (GPLv3)
Classifier: Operating System :: OS Independent
